pybci/__init__.py
pybci/cli.py
pybci/pybci.py
pybci/version.py
pybci_package-1.5.1.dist-info/LICENSE
pybci_package-1.5.1.dist-info/METADATA
pybci_package-1.5.1.dist-info/WHEEL
pybci_package-1.5.1.dist-info/entry_points.txt
pybci_package-1.5.1.dist-info/top_level.txt
pybci_package-1.5.1.dist-info/RECORD
