Metadata-Version: 2.1
Name: pybci-package
Version: 1.5.1
Summary: A Python interface to create a BCI with the Lab Streaming Layer, Pytorch, SciKit-Learn and Tensorflow packages
Author-email: Liam Booth <liambooth123@hotmail.co.uk>
License: MIT
Project-URL: Homepage, https://github.com/lmbooth/pybci
Keywords: machine-learning,tensorflow,sklearn,pytorch,human-computer-interaction,bci,lsl,brain-computer-interface,labstreaminglayer
Classifier: Development Status :: 5 - Production/Stable
Classifier: Intended Audience :: Developers
Classifier: Intended Audience :: Science/Research
Classifier: Intended Audience :: Healthcare Industry
Classifier: Topic :: Scientific/Engineering :: Human Machine Interfaces
Classifier: Topic :: Scientific/Engineering :: Bio-Informatics
Classifier: Topic :: Scientific/Engineering :: Medical Science Apps.
Classifier: Topic :: Scientific/Engineering :: Artificial Intelligence
Classifier: Topic :: Scientific/Engineering
Classifier: License :: OSI Approved :: MIT License
Classifier: Operating System :: Microsoft :: Windows
Classifier: Operating System :: POSIX :: Linux
Classifier: Operating System :: MacOS
Classifier: Programming Language :: Python :: 3.9
Classifier: Programming Language :: Python :: 3.10
Classifier: Programming Language :: Python :: 3.11
Classifier: Programming Language :: Python :: 3.12
Requires-Python: <3.13,>=3.9
License-File: LICENSE
Requires-Dist: numpy>=1.21
Requires-Dist: pylsl==1.16.1
Requires-Dist: scipy>=1.11.1
Requires-Dist: antropy>=0.1.6
Requires-Dist: tensorflow>=2.13.0
Requires-Dist: scikit-learn>=1.3.0
Requires-Dist: torch>=2.0.1
